{
	"animations": [
		{
			"offsets": [
				0,
				0
			],
			"loop": false,
			"fps": 30,
			"anim": "idle",
			"indices": [],
			"name": "Idle"
		},
		{
			"offsets": [
				0,
				0
			],
			"loop": false,
			"fps": 30,
			"anim": "singLEFT",
			"indices": [],
			"name": "Left"
		},
		{
			"offsets": [
				0,
				0
			],
			"loop": false,
			"fps": 30,
			"anim": "singDOWN",
			"indices": [],
			"name": "Down"
		},
		{
			"offsets": [
				0,
				0
			],
			"loop": false,
			"fps": 30,
			"anim": "singUP",
			"indices": [],
			"name": "Up"
		},
		{
			"offsets": [
				0,
				0
			],
			"loop": false,
			"fps": 30,
			"anim": "singRIGHT",
			"indices": [],
			"name": "Right"
		},
		{
			"offsets": [
				0,
				0
			],
			"loop": false,
			"fps": 30,
			"anim": "singLEFTmiss",
			"indices": [],
			"name": "Left"
		},
		{
			"offsets": [
				0,
				0
			],
			"loop": false,
			"fps": 30,
			"anim": "singDOWNmiss",
			"indices": [],
			"name": "Left"
		},
		{
			"offsets": [
				0,
				0
			],
			"loop": false,
			"fps": 30,
			"anim": "singUPmiss",
			"indices": [],
			"name": "Left"
		},
		{
			"offsets": [
				0,
				0
			],
			"loop": false,
			"fps": 30,
			"anim": "singRIGHTmiss",
			"indices": [],
			"name": "Left"
		},
		{
			"offsets": [
				0,
				0
			],
			"loop": false,
			"fps": 30,
			"anim": "hey",
			"indices": [],
			"name": "Left"
		},
		{
			"offsets": [
				0,
				0
			],
			"loop": false,
			"fps": 30,
			"anim": "hurt",
			"indices": [],
			"name": "Left"
		},
		{
			"offsets": [
				-4,
				0
			],
			"loop": true,
			"fps": 30,
			"anim": "scared",
			"indices": [],
			"name": "Left"
		},
		{
			"offsets": [
				0,
				0
			],
			"loop": false,
			"fps": 30,
			"anim": "dodge",
			"indices": [],
			"name": "Left"
		},
		{
			"offsets": [
				0,
				0
			],
			"loop": false,
			"fps": 30,
			"anim": "attack",
			"indices": [],
			"name": "Left"
		},
		{
			"offsets": [
				0,
				0
			],
			"loop": false,
			"fps": 30,
			"anim": "pre-attack",
			"indices": [],
			"name": "Left"
		},
		{
			"offsets": [
				0,
				0
			],
			"loop": false,
			"fps": 30,
			"anim": "singLEFT-alt",
			"indices": [],
			"name": "AltLeft"
		},
		{
			"offsets": [
				0,
				0
			],
			"loop": false,
			"fps": 30,
			"anim": "singDOWN-alt",
			"indices": [],
			"name": "AltDown"
		},
		{
			"offsets": [
				0,
				0
			],
			"loop": false,
			"fps": 30,
			"anim": "singUP-alt",
			"indices": [],
			"name": "AltUp"
		},
		{
			"offsets": [
				0,
				0
			],
			"loop": false,
			"fps": 30,
			"anim": "singRIGHT-alt",
			"indices": [],
			"name": "AltRight"
		}
	],
	"vocals_file": "",
	"no_antialiasing": true,
	"image": "characters/TRex",
	"position": [
		60,
		310
	],
	"healthicon": "BF",
	"flip_x": false,
	"healthbar_colors": [
		55,
		187,
		2
	],
	"camera_position": [
		60,
		0
	],
	"sing_duration": 12,
	"scale": 1,
	"_editor_isPlayer": false
}